<annotation>
	<folder>Open_circuit</folder>
	<filename>09_open_circuit_07.jpg</filename>
	<path>/home/weapon/Desktop/PCB_DATASET/Open_circuit/09_open_circuit_07.jpg</path>
	<source>
		<database>Unknown</database>
	</source>
	<size>
		<width>640</width>
		<height>640</height>
		<depth>3</depth>
	</size>
	<segmented>0</segmented>
	<object>
		<name>open_circuit</name>
		<pose>Unspecified</pose>
		<truncated>0</truncated>
		<difficult>0</difficult>
		<bndbox>
			<xmin>421</xmin>
			<ymin>437</ymin>
			<xmax>432</xmax>
			<ymax>450</ymax>
		</bndbox>
	</object>
	<object>
		<name>open_circuit</name>
		<pose>Unspecified</pose>
		<truncated>0</truncated>
		<difficult>0</difficult>
		<bndbox>
			<xmin>511</xmin>
			<ymin>306</ymin>
			<xmax>519</xmax>
			<ymax>319</ymax>
		</bndbox>
	</object>
	<object>
		<name>open_circuit</name>
		<pose>Unspecified</pose>
		<truncated>0</truncated>
		<difficult>0</difficult>
		<bndbox>
			<xmin>528</xmin>
			<ymin>535</ymin>
			<xmax>539</xmax>
			<ymax>547</ymax>
		</bndbox>
	</object>
	<object>
		<name>open_circuit</name>
		<pose>Unspecified</pose>
		<truncated>0</truncated>
		<difficult>0</difficult>
		<bndbox>
			<xmin>80</xmin>
			<ymin>498</ymin>
			<xmax>95</xmax>
			<ymax>514</ymax>
		</bndbox>
	</object>
	<object>
		<name>open_circuit</name>
		<pose>Unspecified</pose>
		<truncated>0</truncated>
		<difficult>0</difficult>
		<bndbox>
			<xmin>556</xmin>
			<ymin>464</ymin>
			<xmax>566</xmax>
			<ymax>474</ymax>
		</bndbox>
	</object>
</annotation>